LICENSE
MANIFEST.in
README.md
setup.py
ci_analysis.egg-info/PKG-INFO
ci_analysis.egg-info/SOURCES.txt
ci_analysis.egg-info/dependency_links.txt
ci_analysis.egg-info/entry_points.txt
ci_analysis.egg-info/requires.txt
ci_analysis.egg-info/top_level.txt
cia/__init__.py
cia/__main__.py
cia/analysis.py
cia/buildkite.py
cia/cfg.py
cia/cia.py
cia/filter.py
cia/plot.py
cia/utils.py