Metadata-Version: 2.1
Name: ci-analysis
Version: 0.0.0
Summary: Performs analysis on CI build information.
Home-page: https://github.com/jgehrcke/ci-analysis
Author: Dr. Jan-Philip Gehrcke
Author-email: jgehrcke@googlemail.com
License: UNKNOWN
Platform: UNKNOWN
Classifier: License :: OSI Approved :: MIT License
Classifier: Programming Language :: Python
Classifier: Programming Language :: Python :: 3.8
Classifier: Programming Language :: Python :: Implementation :: CPython
Classifier: Operating System :: POSIX
